djangomini/__init__.py
djangomini/controllers.py
djangomini/models.py
djangomini/tools.py
djangomini/urls.py
djangomini-1.0.0b5.dist-info/DESCRIPTION.rst
djangomini-1.0.0b5.dist-info/METADATA
djangomini-1.0.0b5.dist-info/RECORD
djangomini-1.0.0b5.dist-info/WHEEL
djangomini-1.0.0b5.dist-info/metadata.json
djangomini-1.0.0b5.dist-info/top_level.txt
