Metadata-Version: 2.0
Name: djangomini
Version: 1.0.0b5
Summary: Django(mini) - Infrastructure for rapid development on Django.
Home-page: https://github.com/djangomini/djangomini
Author: Anton Danilchenko
Author-email: anton@danilchenko.me
License: MIT
Keywords: django web framework
Platform: any
Classifier: Development Status :: 4 - Beta
Classifier: Environment :: Web Environment
Classifier: Intended Audience :: Developers
Classifier: License :: OSI Approved :: MIT License
Classifier: Operating System :: OS Independent
Classifier: Programming Language :: Python
Classifier: Programming Language :: Python :: 3
Classifier: Programming Language :: Python :: 3.5
Classifier: Topic :: Internet :: WWW/HTTP :: Dynamic Content
Classifier: Topic :: Software Development :: Libraries :: Python Modules
Requires-Dist: django
